3rd-Sem-CSE/DDCO/LAB/LAB-V/T-Flip_Flop/tff.v
module tff (input wire T, input wire clk, output reg Q);
initial Q = 0;
always @(posedge clk )
	begin  
    if (T)    Q <= ~Q;   // toggle  
    else    Q <= Q;    // hold
  end
endmodule

3rd-Sem-CSE/DDCO/LAB/LAB-V/T-Flip_Flop/tff_tb.v
module TB_T; 
reg T;  
reg CLK;  
wire Q; 
 // Instantiate T flip-flop 
 tff newT (.T(T), .clk(CLK), .Q(Q));
// Clock generation: 10 time units period  
initial 
begin
    CLK = 1'b0;    
forever #5 CLK = ~CLK;  
end
// Waveform dump 
 initial 
begin   
 $dumpfile("tff.vcd");   
 $dumpvars(0, TB_T);  
end  
initial 
begin   
$monitor("Time=%0t T=%b | Q=%b", $time,T, Q);
  end
initial
begin 
   T = 1'b0;
   #7 T = 1'b1;
   #50 T = 1'b0;
   #20 $finish; 
end

initial
begin 
   #200 $finish; 
end
endmodule

3rd-Sem-CSE/DDCO/LAB/LAB-V/T-Flip_Flop/tff.vcd
$date
	Fri Sep 12 19:45:01 2025
$end
$version
	Icarus Verilog
$end
$timescale
	1s
$end
$scope module TB_T $end
$var wire 1 ! Q $end
$var reg 1 " CLK $end
$var reg 1 # T $end
$scope module newT $end
$var wire 1 # T $end
$var wire 1 " clk $end
$var reg 1 ! Q $end
$upscope $end
$upscope $end
$enddefinitions $end
$comment Show the parameter values. $end
$dumpall
$end
#0
$dumpvars
0#
0"
0!
$end
#5
1"
#7
1#
#10
0"
#15
1!
1"
#20
0"
#25
0!
1"
#30
0"
#35
1!
1"
#40
0"
#45
0!
1"
#50
0"
#55
1!
1"
#57
0#
