3rd-Sem-CSE/DDCO/LAB/LAB-II/S2/simple.v
module   or2(c, a, b);
    input a;
    input b;
    output c;
    assign c = a | b;
    
endmodule
module  and2(c, a, b);
    input a;
    input b;
    output c;
    assign c = a&b;
    
endmodule

module simple_circuit2(A, B, C, Y);

    input A, B, C;
    output Y;
    wire w1;

    and2 and2_1(w1, B, C);
    or2 or2_2(Y, A, w1);
endmodule

3rd-Sem-CSE/DDCO/LAB/LAB-II/S2/simple_tb.v
module simple_circuit2_tb;
    reg A, B, C;
    wire Y;
    simple_circuit2 M1 (A, B, C, Y);
    initial begin
        #0 A = 1'b0;B = 1'b0;C = 1'b0;
        #20 A = 1'b0;B = 1'b0;C = 1'b1;
        #20 A = 1'b0;B = 1'b1;C = 1'b0;
        #20 A = 1'b0;B = 1'b1;C = 1'b1;
        #20 A = 1'b1;B = 1'b0;C = 1'b0;
        #20 A = 1'b1;B = 1'b0;C = 1'b1;
        #20 A = 1'b1;B = 1'b1;C = 1'b0;
        #20 A = 1'b1;B = 1'b1;C = 1'b1;
    end
    initial begin
        $monitor($time, "A = %b, B = %b, C = %b, Y = %b", A, B, C, Y);
    end
    initial begin
        $dumpfile("s2.vcd");
        $dumpvars(0, simple_circuit2_tb);
    end
endmodule

3rd-Sem-CSE/DDCO/LAB/LAB-II/S2/s2.vcd
$date
	Fri Aug 22 14:54:56 2025
$end
$version
	Icarus Verilog
$end
$timescale
	1s
$end
$scope module simple_circuit2_tb $end
$var wire 1 ! Y $end
$var reg 1 " A $end
$var reg 1 # B $end
$var reg 1 $ C $end
$scope module M1 $end
$var wire 1 " A $end
$var wire 1 # B $end
$var wire 1 $ C $end
$var wire 1 % w1 $end
$var wire 1 ! Y $end
$scope module and2_1 $end
$var wire 1 # a $end
$var wire 1 $ b $end
$var wire 1 % c $end
$upscope $end
$scope module or2_2 $end
$var wire 1 " a $end
$var wire 1 % b $end
$var wire 1 ! c $end
$upscope $end
$upscope $end
$upscope $end
$enddefinitions $end
$comment Show the parameter values. $end
$dumpall
$end
#0
$dumpvars
0%
0$
0#
0"
0!
$end
#20
1$
#40
0$
1#
#60
1!
1%
1$
#80
0%
0$
0#
1"
#100
1$
#120
0$
1#
#140
1%
1$
