3rd-Sem-CSE/DDCO/LAB/Done_Part/LAB-IV/JKFF/jkff.v
module jkff (input wire j, input wire k,input wire clk,  input wire rst,output reg q );
    always @(posedge clk or posedge rst) 
    begin       
    if (rst)            q <= 1'b0;                // Reset to 0       
    else begin case ({j, k})             
        2'b00: q <= q;        // No change       
        2'b01: q <= 1'b0;     // Reset       
        2'b10: q <= 1'b1;     // Set            
        2'b11: q <= ~q;       // Toggle          
    endcase       
    end 
    end
endmodule

3rd-Sem-CSE/DDCO/LAB/LAB-IV/JKFF/jkfftb.v
`timescale 1ns/1ps
module tb_jk_ff;   
reg j, k, clk;    
wire q;   
 // Instantiate JK flip-flop 
jkff jk1 (.j(j),.k(k),.clk(clk),.q(q));  
// Generate clock
initial begin   
    clk = 0;      
forever #5 clk = ~clk;   // Clock period = 10 ns   
end
initial
begin
// waveform dump 
$dumpfile("jkff.vcd");   
$dumpvars(0, tb_jk_ff);  
end
// Test sequence    
initial begin        // Monitor outputs   
    $monitor("Time=%0t | J=%b K=%b | Q=%b", $time, j, k, q);      
    // Initialize        j = 0; k = 0;       
    // Apply inputs on different clock edges      
    #10 j = 0; k = 0;   // Hold  
    #10 j = 0; k = 1;   // Reset  
    #10 j = 1; k = 0;   // Set       
    #10 j = 1; k = 1;   // Toggle   
    #10 j = 1; k = 1;   // Toggle again       
    #10 j = 0; k = 1;   // Reset        
    #10 j = 1; k = 0;   // Set      
    #20 $finish;    
end
endmodule

3rd-Sem-CSE/DDCO/LAB/LAB-IV/JKFF/jkff.vcd
$date
	Mon Sep 08 14:40:33 2025
$end
$version
	Icarus Verilog
$end
$timescale
	1ps
$end
$scope module tb_jk_ff $end
$var wire 1 ! q $end
$var reg 1 " clk $end
$var reg 1 # j $end
$var reg 1 $ k $end
$scope module jk1 $end
$var wire 1 " clk $end
$var wire 1 # j $end
$var wire 1 $ k $end
$var wire 1 % rst $end
$var reg 1 ! q $end
$upscope $end
$upscope $end
$enddefinitions $end
$comment Show the parameter values. $end
$dumpall
$end
#0
$dumpvars
z%
x$
x#
0"
x!
$end
#5000
1"
#10000
0"
0$
0#
#15000
1"
#20000
0"
1$
#25000
0!
1"
#30000
0"
0$
1#
#35000
1!
1"
#40000
0"
1$
#45000
0!
1"
#50000
0"
#55000
1!
1"
#60000
0"
0#
#65000
0!
1"
#70000
0"
0$
1#
#75000
1!
1"
