3rd-Sem-CSE/DDCO/LAB/LAB-IV/TFF_to_DFF_assign/tfftodff.v
module tff (input wire T, input wire clk, input wire rst, output reg Q);
always @(posedge clk )
	 begin  if (rst) 
                   Q <= 1'b0;  
                 else if (T)    Q <= ~Q;   // toggle  
	else    Q <= Q;    // hold
end
endmodule

module xorgate (y,a,b);
    input a,b;
    output y;
    assign y = a ^ b;
endmodule

module tfftodff (input wire D, input wire clk, input wire rst, output wire Q);
  wire T;
  xorgate x(T, D, Q);
  tff t1(T,clk,rst, Q);
endmodule

3rd-Sem-CSE/DDCO/LAB/Done_Part/LAB-IV/TFF_to_DFF_assign/tfftodfftb.v
module TB_D; 
reg D;  
reg CLK;  
reg RST;  
wire Q; 
tfftodff newD (.D(D), .clk(CLK), .rst(RST), .Q(Q)); 
 // clock  
initial begin   
  CLK = 1'b0;  
  forever #5 CLK = ~CLK;  
end  
initial
begin
// waveform dump 
$dumpfile("tfftodff.vcd");   
$dumpvars(0, TB_D);  
end
initial 
begin  
    $monitor($time, " CLK=%b, D=%b, RESET=%b, Q=%b", CLK, D, RST, Q);
    RST = 1'b1; 
    D = 1'b0; #9;  
    RST = 1'b0; #6; 
    D = 1'b1; #7;    
    D = 1'b0; #9;    
    D = 1'b1; #11;  
    D = 1'b0; #6;    
    RST = 1'b1; #5;
    RST = 1'b0; #15;    
    $finish;
end
initial
begin  
    #200 $finish; 
end
endmodule

3rd-Sem-CSE/DDCO/LAB/LAB-IV/TFF_to_DFF_assign/tfftodff.vcd
$date
	Mon Sep 08 15:27:28 2025
$end
$version
	Icarus Verilog
$end
$timescale
	1s
$end
$scope module TB_D $end
$var wire 1 ! Q $end
$var reg 1 " CLK $end
$var reg 1 # D $end
$var reg 1 $ RST $end
$scope module newD $end
$var wire 1 # D $end
$var wire 1 " clk $end
$var wire 1 $ rst $end
$var wire 1 % T $end
$var wire 1 ! Q $end
$scope module t1 $end
$var wire 1 " clk $end
$var wire 1 $ rst $end
$var wire 1 % T $end
$var reg 1 ! Q $end
$upscope $end
$scope module x $end
$var wire 1 # a $end
$var wire 1 ! b $end
$var wire 1 % y $end
$upscope $end
$upscope $end
$upscope $end
$enddefinitions $end
$comment Show the parameter values. $end
$dumpall
$end
#0
$dumpvars
x%
1$
0#
0"
x!
$end
#5
0%
0!
1"
#9
0$
#10
0"
#15
1!
0%
1"
1#
#20
0"
#22
1%
0#
#25
0%
0!
1"
#30
0"
#31
1%
1#
#35
0%
1!
1"
#40
0"
#42
1%
0#
#45
0%
0!
1"
#48
1$
#50
0"
#53
0$
