3rd-Sem-CSE/DDCO/LAB/LAB-V/JK_Flip_Flop/jkff.v
module jkff (input wire j, input wire k,input wire clk,output reg q );
initial q = 0;
    always @(posedge clk) 
    begin       
    begin case ({j, k})             
        2'b00: q <= q;        // No change       
        2'b01: q <= 1'b0;     // Reset       
        2'b10: q <= 1'b1;     // Set            
        2'b11: q <= ~q;       // Toggle          
    endcase       
    end 
    end
endmodule

3rd-Sem-CSE/DDCO/LAB/LAB-V/JK_Flip_Flop/jkff_tb.v
module tb_jk_ff;   
reg j, k, clk;    
wire q;   
 // Instantiate JK flip-flop 
jkff jk1 (.j(j),.k(k),.clk(clk),.q(q));  
// Generate clock
initial begin   
    clk = 0;      
forever #5 clk = ~clk;   
end
initial
begin
// waveform dump 
$dumpfile("jkff.vcd");   
$dumpvars(0, tb_jk_ff);  
end
// Test sequence    
initial begin        // Monitor outputs   
    $monitor("Time=%0t | J=%b K=%b | Q=%b", $time, j, k, q);      
    j = 0; k = 0;            
    #10 j = 0; k = 0;   // Hold  
    #10 j = 0; k = 1;   // Reset  
    #10 j = 1; k = 0;   // Set       
    #10 j = 1; k = 1;   // Toggle   
    #10 j = 1; k = 1;   // Toggle again       
    #10 j = 0; k = 1;   // Reset        
    #10 j = 1; k = 0;   // Set      
    #20 $finish;    
end
endmodule

3rd-Sem-CSE/DDCO/LAB/LAB-V/JK_Flip_Flop/jkff.vcd
$date
	Fri Sep 12 19:51:13 2025
$end
$version
	Icarus Verilog
$end
$timescale
	1s
$end
$scope module tb_jk_ff $end
$var wire 1 ! q $end
$var reg 1 " clk $end
$var reg 1 # j $end
$var reg 1 $ k $end
$scope module jk1 $end
$var wire 1 " clk $end
$var wire 1 # j $end
$var wire 1 $ k $end
$var reg 1 ! q $end
$upscope $end
$upscope $end
$enddefinitions $end
$comment Show the parameter values. $end
$dumpall
$end
#0
$dumpvars
0$
0#
0"
0!
$end
#5
1"
#10
0"
#15
1"
#20
0"
1$
#25
1"
#30
0"
0$
1#
#35
1!
1"
#40
0"
1$
#45
0!
1"
#50
0"
#55
1!
1"
#60
0"
0#
#65
0!
1"
#70
0"
0$
1#
#75
1!
1"
