3rd-Sem-CSE/DDCO/LAB/LAB-II/S1/simple.v
module simple_circuit (A,B,C,D,E);

    output D, E;
    input A, B, C;
    wire w1;
    and G1 (w1, A, B);
    not G2 (E, C);
    or G3 (D, w1, E);
endmodule

3rd-Sem-CSE/DDCO/LAB/LAB-II/S1/simple_tb.v
module tb_simple_circuit1;
reg A, B, C;
wire Y;
simple_circuit M1(A, B, C, D, E);
initial begin
        #0 A = 1'b0;B = 1'b0;C = 1'b0;
        #20 A = 1'b0;B = 1'b0;C = 1'b1;
        #20 A = 1'b0;B = 1'b1;C = 1'b0;
        #20 A = 1'b0;B = 1'b1;C = 1'b1;
        #20 A = 1'b1;B = 1'b0;C = 1'b0;
        #20 A = 1'b1;B = 1'b0;C = 1'b1;
        #20 A = 1'b1;B = 1'b1;C = 1'b0;
        #20 A = 1'b1;B = 1'b1;C = 1'b1;
end

initial begin
    $monitor($time, "A = %b, B = %b, C = %b, D = %b, E = %b", A, B, C, D, E);
end
initial begin
    $dumpfile("s1.vcd");
    $dumpvars(0, tb_simple_circuit1);
end
endmodule

3rd-Sem-CSE/DDCO/LAB/LAB-II/S1/s1.vcd
$date
	Fri Aug 22 14:53:12 2025
$end
$version
	Icarus Verilog
$end
$timescale
	1s
$end
$scope module tb_simple_circuit1 $end
$var wire 1 ! E $end
$var wire 1 " D $end
$var reg 1 # A $end
$var reg 1 $ B $end
$var reg 1 % C $end
$scope module M1 $end
$var wire 1 # A $end
$var wire 1 $ B $end
$var wire 1 % C $end
$var wire 1 " D $end
$var wire 1 ! E $end
$var wire 1 & w1 $end
$upscope $end
$upscope $end
$enddefinitions $end
$comment Show the parameter values. $end
$dumpall
$end
#0
$dumpvars
0&
0%
0$
0#
1"
1!
$end
#20
0"
0!
1%
#40
1"
1!
0%
1$
#60
0"
0!
1%
#80
1"
1!
0%
0$
1#
#100
0"
0!
1%
#120
1"
1!
1&
0%
1$
#140
0!
1%
