3rd-Sem-CSE/DDCO/LAB/LAB-V/D_Flip_Flop/dff.v
module dff (input wire D, input wire clk, output reg Q);
  always @(posedge clk) 
    begin  

      Q <= D; // Sample D on rising edge of clock
    end
endmodule

3rd-Sem-CSE/DDCO/LAB/LAB-V/D_Flip_Flop/dff_tb.v
module TB_D; 
reg D;  
reg CLK;   
wire Q; 
dff newD (.D(D), .clk(CLK),.Q(Q)); 
 // clock  
initial begin   
  CLK = 1'b0;  
  forever #5 CLK = ~CLK;  
end  
initial
begin
// waveform dump 
$dumpfile("dff.vcd");   
$dumpvars(0, TB_D);  
end
initial 
begin  
    $monitor($time, " CLK=%b, D=%b, Q=%b", CLK, D, Q);   
    D = 1'b1; #7;    
    D = 1'b0; #9;    
    D = 1'b1; #11;  
    D = 1'b0; #6;
    D = 1'b1; #12;  
    D = 1'b0; #8;         
    $finish;
end
initial
begin  
    #200 $finish; 
end
endmodule

3rd-Sem-CSE/DDCO/LAB/LAB-V/D_Flip_Flop/dff.vcd
$date
	Fri Sep 12 19:41:50 2025
$end
$version
	Icarus Verilog
$end
$timescale
	1s
$end
$scope module TB_D $end
$var wire 1 ! Q $end
$var reg 1 " CLK $end
$var reg 1 # D $end
$scope module newD $end
$var wire 1 # D $end
$var wire 1 " clk $end
$var reg 1 ! Q $end
$upscope $end
$upscope $end
$enddefinitions $end
$comment Show the parameter values. $end
$dumpall
$end
#0
$dumpvars
1#
0"
x!
$end
#5
1!
1"
#7
0#
#10
0"
#15
0!
1"
#16
1#
#20
0"
#25
1!
1"
#27
0#
#30
0"
#33
1#
#35
1"
#40
0"
#45
0!
1"
0#
