3rd-Sem-CSE/DDCO/LAB/LAB-V/T_to_D_Flip_flop/t_to_d.v
module tff (input wire T, input wire clk, output reg Q);
initial Q = 0;
always @(posedge clk )
	 begin
     if (T)    Q <= ~Q;   // toggle  
	else    Q <= Q;    // hold
end
endmodule

module xorgate (y,a,b);
    input a,b;
    output y;
    assign y = a ^ b;
endmodule

module tfftodff (input wire D, input wire clk, output wire Q);
  wire T;
  xorgate x(T, D, Q);
  tff t1(T,clk, Q);
endmodule

3rd-Sem-CSE/DDCO/LAB/LAB-V/T_to_D_Flip_flop/t_to_d_tb.v
module TB_D; 
reg D;  
reg CLK;    
wire Q; 
tfftodff newD (.D(D), .clk(CLK), .Q(Q)); 
 // clock  
initial begin   
  CLK = 1'b0;  
  forever #5 CLK = ~CLK;  
end  
initial
begin
// waveform dump 
$dumpfile("tfftodff.vcd");   
$dumpvars(0, TB_D);  
end
initial 
begin  
    $monitor($time, " CLK=%b, D=%b, Q=%b", CLK, D, Q);
    D = 0;
  @(negedge CLK); D = 1;
  @(negedge CLK); D = 0;
  @(negedge CLK); D = 1;
  @(negedge CLK); D = 0;
  #20 $finish;
    $finish;
end
initial
begin  
    #200 $finish; 
end
endmodule

3rd-Sem-CSE/DDCO/LAB/LAB-V/T_to_D_Flip_flop/tfftodff.vcd
$date
	Fri Sep 12 19:59:21 2025
$end
$version
	Icarus Verilog
$end
$timescale
	1s
$end
$scope module TB_D $end
$var wire 1 ! Q $end
$var reg 1 " CLK $end
$var reg 1 # D $end
$scope module newD $end
$var wire 1 # D $end
$var wire 1 " clk $end
$var wire 1 $ T $end
$var wire 1 ! Q $end
$scope module t1 $end
$var wire 1 " clk $end
$var wire 1 $ T $end
$var reg 1 ! Q $end
$upscope $end
$scope module x $end
$var wire 1 # a $end
$var wire 1 ! b $end
$var wire 1 $ y $end
$upscope $end
$upscope $end
$upscope $end
$enddefinitions $end
$comment Show the parameter values. $end
$dumpall
$end
#0
$dumpvars
0$
0#
0"
0!
$end
#5
1"
#10
1$
1#
0"
#15
0$
1!
1"
#20
1$
0#
0"
#25
0$
0!
1"
#30
1$
1#
0"
#35
0$
1!
1"
#40
1$
0#
0"
#45
0$
0!
1"
