3rd-Sem-CSE/DDCO/LAB/LAB-II/S3/simple.v
/*
 T(Temperature) = 1
 P(Present) = 1

 --> Run Fan
*/
module   or2(c, a, b);
    input a;
    input b;
    output c;
    assign c = a | b;
    
endmodule
module  and2(c, a, b);
    input a;
    input b;
    output c;
    assign c = a&b;
    
endmodule

module fan(D, T, P, O);
input T, P, O;
output D;
wire and_out;
and2 G1(and_out, T, P);
or2 G2(D, O, and_out);

endmodule

3rd-Sem-CSE/DDCO/LAB/LAB-II/S3/simple_tb.v
module simple_circuit3_tb;
    reg T, P, O;
    fan M1(D, T, P, O);
    initial begin
        #0  O = 1'b0;T = 1'b0;P = 1'b0;
        #20 O = 1'b0;T = 1'b0;P = 1'b1;
        #20 O = 1'b0;T = 1'b1;P = 1'b0;
        #20 O = 1'b0;T = 1'b1;P = 1'b1;
        #20 O = 1'b1;T = 1'b0;P = 1'b0;
        #20 O = 1'b1;T = 1'b0;P = 1'b1;
        #20 O = 1'b1;T = 1'b1;P = 1'b0;
        #20 O = 1'b1;T = 1'b1;P = 1'b1;
    end
    initial begin
        $monitor($time, " O = %b, T = %b, P = %b, D = %b", O, T, P, D);
    end
    initial begin
        $dumpfile("s3.vcd");
        $dumpvars(0, simple_circuit3_tb);
    end
endmodule

3rd-Sem-CSE/DDCO/LAB/LAB-II/S3/s3.vcd
$date
	Sat Aug 23 14:26:58 2025
$end
$version
	Icarus Verilog
$end
$timescale
	1s
$end
$scope module simple_circuit3_tb $end
$var wire 1 ! D $end
$var reg 1 " O $end
$var reg 1 # P $end
$var reg 1 $ T $end
$scope module M1 $end
$var wire 1 " O $end
$var wire 1 # P $end
$var wire 1 $ T $end
$var wire 1 % and_out $end
$var wire 1 ! D $end
$scope module G1 $end
$var wire 1 $ a $end
$var wire 1 # b $end
$var wire 1 % c $end
$upscope $end
$scope module G2 $end
$var wire 1 " a $end
$var wire 1 % b $end
$var wire 1 ! c $end
$upscope $end
$upscope $end
$upscope $end
$enddefinitions $end
$comment Show the parameter values. $end
$dumpall
$end
#0
$dumpvars
0%
0$
0#
0"
0!
$end
#20
1#
#40
0#
1$
#60
1!
1%
1#
#80
0%
0#
0$
1"
#100
1#
#120
0#
1$
#140
1%
1#
